yulu/__init__.py
yulu-0.0.1.dist-info/METADATA
yulu-0.0.1.dist-info/WHEEL
yulu-0.0.1.dist-info/top_level.txt
yulu-0.0.1.dist-info/RECORD
