Metadata-Version: 2.1
Name: yulu
Version: 0.0.1
Summary: Yulu for code utilities
Author: Anonymous
Author-email: <mohammedfaisal3366@gmail.com>
Keywords: python
